MedatechUK/__init__.py
MedatechUK/APY/PriDate.py
MedatechUK/APY/Serial.py
MedatechUK/APY/__init__.py
MedatechUK/APY/apy.py
MedatechUK/APY/cl.py
MedatechUK/APY/epdm.py
MedatechUK/APY/mLog.py
MedatechUK/APY/oDataConfig.py
MedatechUK/APY/odata.py
MedatechUK/APY/svc.py
MedatechUK.APY-0.0.27.dist-info/METADATA
MedatechUK.APY-0.0.27.dist-info/WHEEL
MedatechUK.APY-0.0.27.dist-info/licence
MedatechUK.APY-0.0.27.dist-info/top_level.txt
MedatechUK.APY-0.0.27.dist-info/RECORD
