Metadata-Version: 2.1
Name: MedatechUK.APY
Version: 0.0.27
Summary: MedatechUK Python API for Priority oData
Home-page: https://github.com/MedatechUK/Medatech.APY
Author: Simon Barnett
Author-email: si@medatechuk.com
Project-URL: Bug Tracker, https://github.com/MedatechUK/Medatech.APY/issues
Classifier: Programming Language :: Python :: 3
Classifier: License :: OSI Approved :: GNU General Public License (GPL)
Classifier: Operating System :: OS Independent
Requires-Python: >=3.9
License-File: licence
Provides-Extra: dicttoxml
Requires-Dist: dicttoxml >=1.7.16 ; extra == 'dicttoxml'
Provides-Extra: pyodbc
Requires-Dist: pyodbc >=5.0 ; extra == 'pyodbc'
Provides-Extra: pywin32
Requires-Dist: pywin32 >=306 ; extra == 'pywin32'
Provides-Extra: xmltodict
Requires-Dist: xmltodict >=0.13 ; extra == 'xmltodict'
